<?xml version="1.0" encoding="UTF-8"?>
<record xmlns="info:srw/schema/5/picaXML-v1.0" xmlns:xsi="http://www.w3.org/2001/XMLSchema-instance"
    xsi:schemaLocation="info:srw/schema/5/picaXML-v1.0 ./pica-xml-v1-0.xsd">
    <datafield tag="001@">
        <subfield code="0">40</subfield>
    </datafield>
    <datafield tag="001A">
        <subfield code="0">0007:26-07-06</subfield>
    </datafield>
    <datafield tag="001B">
        <subfield code="0">1999:08-04-13</subfield>
        <subfield code="t">00:43:23.000</subfield>
    </datafield>
    <datafield tag="001D">
        <subfield code="0">0007:26-07-06</subfield>
    </datafield>
    <datafield tag="001U">
        <subfield code="0">utf8</subfield>
    </datafield>
    <datafield tag="001X">
        <subfield code="0">0</subfield>
    </datafield>
    <datafield tag="002@">
        <subfield code="0">Oau</subfield>
    </datafield>
    <datafield tag="003@">
        <subfield code="0">514964626</subfield>
    </datafield>
    <datafield tag="003O">
        <subfield code="a">OCoLC</subfield>
        <subfield code="0">836298072</subfield>
        <subfield code="v">2012-12-31</subfield>
    </datafield>
    <datafield tag="007G">
        <subfield code="c">GBV</subfield>
        <subfield code="0">514964626</subfield>
    </datafield>
    <datafield tag="008@">
        <subfield code="b">8</subfield>
    </datafield>
    <datafield tag="008@">
        <subfield code="b">ee</subfield>
    </datafield>
    <datafield tag="009A">
        <subfield code="b">de</subfield>
        <subfield code="c">SUB Göttingen</subfield>
        <subfield code="a">DD2004 A 38</subfield>
    </datafield>
    <datafield tag="009P" occurrence="03">
        <subfield code="S">1</subfield>
        <subfield code="0">cgi</subfield>
        <subfield code="a">http://resolver.sub.uni-goettingen.de/purl?PPN514964626</subfield>
    </datafield>
    <datafield tag="010@">
        <subfield code="a">ger</subfield>
        <subfield code="a">bla</subfield>
    </datafield>
    <datafield tag="011@">
        <subfield code="a">011@.1a </subfield>
        <subfield code="b">011@.1b</subfield>
        <subfield code="c">011@.1c</subfield>
        <subfield code="d">011@.1d</subfield>
        <subfield code="n">011@.1n</subfield>
        <subfield code="e">011@.1e</subfield>
    </datafield>

    <datafield tag="011B">
        <subfield code="a">011Ba - 2006</subfield>
        <subfield code="b">011Bb - 2007</subfield>
        <subfield code="n">011Bn - ...2006</subfield>
    </datafield>
    <datafield tag="016H">
        <subfield code="0">Elektronische Ressource</subfield>
    </datafield>
    <datafield tag="021A">
        <subfield code="a">Ein @schön neu-erfundenes @Kunst-Büchlein</subfield>
        <subfield code="d">Darinnen Hundert fünff und zwantzig Stück, vor Menschen und Vieh,
            sonderlich aber vor reisende Leuthe, wie auch vor die jenigen, so Vieh haben, sehr
            nutzlich zugebrauchen, mit schönen offt probirten Recepten beschrieben ; Welches von mir
            mit sonderbahrem Fleiß aufgesetzt und gut befunden worden ...</subfield>
        <subfield code="h">Heraus gegeben von D. Plein Horati, Königlichen Leib-Medico in Egypten,
            als einem gebohrnen Zigeuner</subfield>
        <subfield code="e">authorInfo</subfield>
        <subfield code="f">parallelTitle</subfield>
    </datafield>
    <datafield tag="021B">
        <subfield code="a">Der @blaue @Brief @bla</subfield>
        <subfield code="d">021B-d</subfield>
        <subfield code="h">021B-h</subfield>
        <subfield code="e">021B-e</subfield>
        <subfield code="f">021B-f</subfield>
    </datafield>
    <datafield tag="021N">
        <subfield code="a">021Na - bla</subfield>
    </datafield>
    <datafield tag="021M">
        <subfield code="a">021Ma - ups</subfield>
        <subfield code="d">021Md - ups</subfield>
        <subfield code="h">021Mh - ups</subfield>
        <subfield code="e">021Me - ups</subfield>
        <subfield code="f">021Mf - ups</subfield>
    </datafield>
    <!--
    <datafield tag="028A">
        <subfield code="P">028A _ Persönlicher Name</subfield>
        <subfield code="d">028A _ Plein</subfield>
        <subfield code="a">028A _ Horath</subfield>
        <subfield code="9">028A _ 48879434X</subfield>
        <subfield code="0">gnd/130053813</subfield>
        <subfield code="c">028A _ ein c</subfield>
        <subfield code="p">028A _ ein p</subfield>
        <subfield code="h">028A _ h - 1972</subfield>
        <subfield code="D">028A _ D - 1972</subfield>
    </datafield>
    -->
    <datafield tag="028B">
        <subfield code="P">028B.1 _ Persönlicher Name</subfield>
        <subfield code="d">028B.1 - Plein</subfield>
        <subfield code="a">028B.1 - Horath</subfield>
        <subfield code="9">028B.1 - 48879434X</subfield>
        <subfield code="0">028B.1 - gnd/130053814</subfield>
        <subfield code="c">028B.1 - ein c</subfield>
        <subfield code="p">028B.1 - ein p</subfield>
        <subfield code="h">028B.1 - h - 1972</subfield>
        <subfield code="D">028B.1 - D - 1972</subfield>
    </datafield>
    <datafield tag="028B">
        <subfield code="P">028B.2 _ Persönlicher Name</subfield>
        <subfield code="d">028B.2 - Plein</subfield>
        <subfield code="a">028B.2 - Horath</subfield>
        <subfield code="9">028B.2 - 48879434X</subfield>
        <subfield code="0">028B.2 - gnd/130053814</subfield>
        <subfield code="c">028B.2 - ein c</subfield>
        <subfield code="p">028B.2 - ein p</subfield>
        <subfield code="h">028B.2 - h - 1972</subfield>
        <subfield code="D">028B.2 - D - 1972</subfield>
    </datafield>


    <datafield tag="028C">
        <subfield code="P">028C _ Persönlicher Name</subfield>
        <subfield code="d">028C - d</subfield>
        <subfield code="a">028C - a</subfield>
        <subfield code="d">028C - d</subfield>
        <subfield code="a">028C - a</subfield>
        <subfield code="9">028C - g</subfield>
        <subfield code="0">gnd/130053815</subfield>
        <subfield code="c">028C - c</subfield>
        <subfield code="p">028C - p</subfield>
        <subfield code="h">028C - h</subfield>
        <subfield code="D">028C - D_1972</subfield>
        <subfield code="B">[Hrsg.]</subfield>
    </datafield>
    <datafield tag="028C">
        <subfield code="P">028C.2 _ Persönlicher Name</subfield>
        <subfield code="d">028C.2 - d</subfield>
        <subfield code="a">028C.2 - a</subfield>
        <subfield code="9">028C.2 - g</subfield>
        <subfield code="0">gnd/130053815</subfield>
        <subfield code="c">028C.2 - c</subfield>
        <subfield code="p">028C.2 - p</subfield>
        <subfield code="h">028C.2 - h</subfield>
        <subfield code="D">028C.2 - D_1972</subfield>
        <subfield code="B">[Hrsg.]</subfield>
    </datafield>
    <datafield tag="028D">
        <subfield code="P">028D.1 _ Persönlicher Name</subfield>
        <subfield code="d">028D.1 - d</subfield>
        <subfield code="a">028D.1 - a</subfield>
        <subfield code="9">028D.1 - g</subfield>
        <subfield code="0">gnd/130053815</subfield>
        <subfield code="c">028D.1 - c</subfield>
        <subfield code="p">028D.1 - p</subfield>
        <subfield code="h">028D.1 - h</subfield>
        <subfield code="D">028D.1 - D_1972</subfield>
        <subfield code="B">[Hrsg.]</subfield>
    </datafield>
    <datafield tag="028D">
        <subfield code="P">028D.2 _ Persönlicher Name</subfield>
        <subfield code="d">028D.2 - d</subfield>
        <subfield code="a">028D.2 - a</subfield>
        <subfield code="9">028D.2 - g</subfield>
        <subfield code="0">gnd/130053815</subfield>
        <subfield code="c">028D.2 - c</subfield>
        <subfield code="p">028D.2 - p</subfield>
        <subfield code="h">028D.2 - h</subfield>
        <subfield code="D">028D.2 - D_1972</subfield>
        <subfield code="B">[Hrsg.]</subfield>
    </datafield>

    <datafield tag="029A">
        <subfield code="a">Hauptkörperschaft (029A)</subfield>
        <subfield code="b">Untergeordnete Körperschaft (029A)</subfield>
        <subfield code="g">Zusatz (029A)</subfield>
        <subfield code="0">gnd/130053825</subfield>
    </datafield>


    <datafield tag="029F">
        <subfield code="a">Hauptkörperschaft (029F)</subfield>
        <subfield code="b">Untergeordnete Körperschaft (029F)</subfield>
        <subfield code="g">Zusatz (029F)</subfield>
        <subfield code="0">gnd/130053825</subfield>
    </datafield>
    <datafield tag="029F">
        <subfield code="a">Hauptkörperschaft (029F2)</subfield>
        <subfield code="b">Untergeordnete Körperschaft (029F2)</subfield>
        <subfield code="g">Zusatz (029F2)</subfield>
        <subfield code="0">gnd/130053825</subfield>
    </datafield>
    
    <datafield tag="032C">
        <subfield code="a">[Online-Ausg.]</subfield>
    </datafield>
    <datafield tag="033A">
        <subfield code="p">033A.1 - pubPlace</subfield>
        <subfield code="n">033A.1 - publisher</subfield>
    </datafield>
    <datafield tag="033A">
        <subfield code="p">033A.2 - pubPlace</subfield>
        <subfield code="n">033A.2 - publisher</subfield>
    </datafield>
    <datafield tag="033J">
        <subfield code="a">033J.1 - name</subfield>
        <subfield code="0">033J.1 - gnd/130053815</subfield>
    </datafield>
    <datafield tag="033J">
        <subfield code="a">033J.2 - name</subfield>
        <subfield code="0">033J.2 - gnd/130053816</subfield>
    </datafield>

    <datafield tag="033B" occurrence="01">
        <subfield code="p">Göttingen</subfield>
        <subfield code="n">Niedersächsische Staats- und Universitätsbibliothek</subfield>
    </datafield>

    <datafield tag="033N">
        <subfield code="p">033N1 - Göttingen</subfield>
        <subfield code="n">033N1 - Niedersächsische Staats- und Universitätsbibliothek</subfield>
    </datafield>

    <datafield tag="033N">
        <subfield code="p">033N2 - Göttingen</subfield>
        <subfield code="n">033N2 - Niedersächsische Staats- und Universitätsbibliothek</subfield>
    </datafield>

    <datafield tag="033O">
        <subfield code="p">033O - Göttingen</subfield>
        <subfield code="n">033O - GDZ</subfield>
    </datafield>
    <datafield tag="033P">
        <subfield code="p">033P - Göttingen</subfield>
        <subfield code="n">033P - DigiWunschbuch</subfield>
    </datafield>
    <datafield tag="034D">
        <subfield code="a">034D</subfield>
    </datafield>
    <datafield tag="034M">
        <subfield code="a">034M</subfield>
    </datafield>
    <datafield tag="034I">
        <subfield code="a">034I</subfield>
    </datafield>
    <datafield tag="037G">
        <subfield code="a">Zugl. digitaler Master</subfield>
    </datafield>
    <datafield tag="037H">
        <subfield code="a">TIFF, Vers.6.0, 600 dpi, 1 bit (s/w), ITU group 4;
            Digitalisierungsvorlage: Primärausgabe</subfield>
    </datafield>
    <datafield tag="044S">
        <subfield code="a">Begriff - 1</subfield>
        <subfield code="g">Zusatz - 1</subfield>
    </datafield>
        
    <datafield tag="045F">
        <subfield code="e">23sdnb</subfield>
        <subfield code="a">490</subfield>
    </datafield>
    <datafield tag="045F">
        <subfield code="e">23sdnb</subfield>
        <subfield code="a">490</subfield>
    </datafield>
    
    <datafield tag="045Q" occurrence="01">
        <subfield code="9">10641593X</subfield>
        <subfield code="a">44.52</subfield>
        <subfield code="j">Therapie</subfield>
        <subfield code="X">Medizin</subfield>
    </datafield>
    <datafield tag="047C">
        <subfield code="a">schönes</subfield>
    </datafield>
    <datafield tag="101@">
        <subfield code="a">40</subfield>
        <subfield code="c">PICA</subfield>
    </datafield>
    <datafield tag="201B" occurrence="01">
        <subfield code="0">15-05-09</subfield>
        <subfield code="t">16:18:35.000</subfield>
    </datafield>
    <datafield tag="201D" occurrence="01">
        <subfield code="0">15-05-09</subfield>
        <subfield code="b">708</subfield>
        <subfield code="a">0007</subfield>
    </datafield>
    <datafield tag="201U" occurrence="01">
        <subfield code="0">utf8</subfield>
    </datafield>
    <datafield tag="203@" occurrence="01">
        <subfield code="0">772721424</subfield>
    </datafield>
    <datafield tag="208@" occurrence="01">
        <subfield code="a">26-07-06</subfield>
        <subfield code="b">x</subfield>
    </datafield>
    <datafield tag="209B" occurrence="01">
        <subfield code="a">Göttingen : Niedersächsische Staats- und
            Universitätsbibliothek</subfield>
        <subfield code="x">75</subfield>
    </datafield>
    <datafield tag="209O" occurrence="01">
        <subfield code="a">DigiWuBu</subfield>
        <subfield code="x">00</subfield>
    </datafield>
    <datafield tag="209R" occurrence="01">
        <subfield code="S">1</subfield>
        <subfield code="0">cgi</subfield>
        <subfield code="a">http://resolver.sub.uni-goettingen.de/purl?PPN514964626</subfield>
    </datafield>
    <datafield tag="220B" occurrence="01">
        <subfield code="a">www-gdz</subfield>
    </datafield>
    <datafield tag="233P" occurrence="01">
        <subfield code="n">DigiWunschbuch</subfield>
    </datafield>
    <datafield tag="245P" occurrence="01">
        <subfield code="a">c</subfield>
    </datafield>
</record>
